keymateapi/__init__.py
keymateapi/sdk.py
keymateapi/sdkconfiguration.py
keymateapi/_hooks/__init__.py
keymateapi/_hooks/sdkhooks.py
keymateapi/_hooks/types.py
keymateapi/models/__init__.py
keymateapi/models/components/__init__.py
keymateapi/models/components/browseresultitem.py
keymateapi/models/components/browsewithproxyresultitem.py
keymateapi/models/components/httpmetadata.py
keymateapi/models/components/searchresultitem.py
keymateapi/models/components/security.py
keymateapi/models/errors/__init__.py
keymateapi/models/errors/browse.py
keymateapi/models/errors/browseurl.py
keymateapi/models/errors/gptsbrowse.py
keymateapi/models/errors/internetsearch.py
keymateapi/models/errors/sdkerror.py
keymateapi/models/errors/search.py
keymateapi/models/errors/ultrafastsearch.py
keymateapi/models/operations/__init__.py
keymateapi/models/operations/browse.py
keymateapi/models/operations/browseurl.py
keymateapi/models/operations/gptsbrowse.py
keymateapi/models/operations/internetsearch.py
keymateapi/models/operations/query.py
keymateapi/models/operations/search.py
keymateapi/models/operations/ultrafastsearch.py
keymateapi/models/operations/upsert.py
keymateapi/utils/__init__.py
keymateapi/utils/retries.py
keymateapi/utils/utils.py
keymateapi-0.4.0.dist-info/METADATA
keymateapi-0.4.0.dist-info/WHEEL
keymateapi-0.4.0.dist-info/top_level.txt
keymateapi-0.4.0.dist-info/RECORD
